pygase/__init__.py
pygase/backend.py
pygase/client.py
pygase/connection.py
pygase/event.py
pygase/gamestate.py
pygase/utils.py
pygase-0.3.1.dist-info/LICENSE
pygase-0.3.1.dist-info/WHEEL
pygase-0.3.1.dist-info/METADATA
pygase-0.3.1.dist-info/RECORD
