Metadata-Version: 2.1
Name: pygase
Version: 0.3.1
Summary: game-ready client-server architecture and UDP-based network protocol - built to be easy to use, lightweight, fast, scalable and reliable
Home-page: https://sbischoff-ai.github.io/pygase/
License: MIT
Keywords: client,server,real-time,network,games
Author: Silas Bischoff
Author-email: silas.bischoff@googlemail.com
Requires-Python: >=3.6,<4.0
Classifier: Development Status :: 4 - Beta
Classifier: Intended Audience :: Developers
Classifier: License :: OSI Approved :: MIT License
Classifier: Operating System :: MacOS
Classifier: Operating System :: Microsoft :: Windows
Classifier: Operating System :: POSIX
Classifier: Programming Language :: Python :: 3
Classifier: Programming Language :: Python :: 3.6
Classifier: Programming Language :: Python :: 3.7
Classifier: Topic :: Games/Entertainment
Classifier: Topic :: Internet
Classifier: Topic :: Software Development
Classifier: Topic :: Software Development :: Libraries
Classifier: Topic :: Software Development :: Libraries :: Python Modules
Classifier: Topic :: System :: Networking
Requires-Dist: curio (>=0.9.0,<0.10.0)
Requires-Dist: ifaddr (>=0.1.6,<0.2.0)
Requires-Dist: u-msgpack-python (>=2.5,<3.0)
Project-URL: Repository, https://github.com/sbischoff-ai/pygase
